Alborz_STT/__init__.py
Alborz_STT-0.1.dist-info/METADATA
Alborz_STT-0.1.dist-info/WHEEL
Alborz_STT-0.1.dist-info/top_level.txt
Alborz_STT-0.1.dist-info/RECORD
