Metadata-Version: 2.1
Name: Alborz_STT
Version: 0.1
Summary: this is a speech to text pacakage create by alborz yzh
Author: Alborz yzh
Author-email: example@gmail.com
